mistrik/__init__.py
mistrik/mistrik.py
mistrik/mistrik_readability.py
mistrik/readability.py
mistrik-1.0.1.dist-info/LICENSE
mistrik-1.0.1.dist-info/METADATA
mistrik-1.0.1.dist-info/WHEEL
mistrik-1.0.1.dist-info/top_level.txt
mistrik-1.0.1.dist-info/RECORD
